[
  {
    "inputs": [],
    "name": "InvalidAmount",
    "type": "error"
  },
  {
    "inputs": [],
    "name": "InvalidFeeBasisPoint",
    "type": "error"
  },
  {
    "inputs": [],
    "name": "InvalidInitialization",
    "type": "error"
  },
  {
    "inputs": [],
    "name": "NotInitializing",
    "type": "error"
  },
  {
    "inputs": [
      {
        "internalType": "address",
        "name": "owner",
        "type": "address"
      }
    ],
    "name": "OwnableInvalidOwner",
    "type": "error"
  },
  {
    "inputs": [
      {
        "internalType": "address",
        "name": "account",
        "type": "address"
      }
    ],
    "name": "OwnableUnauthorizedAccount",
    "type": "error"
  },
  {
    "inputs": [],
    "name": "ZeroAddress",
    "type": "error"
  },
  {
    "anonymous": false,
    "inputs": [
      {
        "indexed": true,
        "internalType": "address",
        "name": "previousRecipient",
        "type": "address"
      },
      {
        "indexed": true,
        "internalType": "address",
        "name": "newRecipient",
        "type": "address"
      }
    ],
    "name": "FeeRecipientUpdated",
    "type": "event"
  },
  {
    "anonymous": false,
    "inputs": [
      {
        "indexed": false,
        "internalType": "uint64",
        "name": "version",
        "type": "uint64"
      }
    ],
    "name": "Initialized",
    "type": "event"
  },
  {
    "anonymous": false,
    "inputs": [
      {
        "indexed": false,
        "internalType": "uint16",
        "name": "maxPositions",
        "type": "uint16"
      }
    ],
    "name": "MaxPositionsUpdated",
    "type": "event"
  },
  {
    "anonymous": false,
    "inputs": [
      {
        "indexed": false,
        "internalType": "uint8",
        "name": "precision",
        "type": "uint8"
      }
    ],
    "name": "MinTokenPrecisionUpdated",
    "type": "event"
  },
  {
    "anonymous": false,
    "inputs": [
      {
        "indexed": true,
        "internalType": "address",
        "name": "previousOwner",
        "type": "address"
      },
      {
        "indexed": true,
        "internalType": "address",
        "name": "newOwner",
        "type": "address"
      }
    ],
    "name": "OwnershipTransferred",
    "type": "event"
  },
  {
    "anonymous": false,
    "inputs": [
      {
        "indexed": false,
        "internalType": "bool",
        "name": "isVaultPaused",
        "type": "bool"
      }
    ],
    "name": "VaultPausedUpdated",
    "type": "event"
  },
  {
    "anonymous": false,
    "inputs": [
      {
        "indexed": false,
        "internalType": "address[]",
        "name": "callers",
        "type": "address[]"
      },
      {
        "indexed": false,
        "internalType": "bool",
        "name": "isWhitelisted",
        "type": "bool"
      }
    ],
    "name": "WhitelistCallersUpdated",
    "type": "event"
  },
  {
    "anonymous": false,
    "inputs": [
      {
        "indexed": false,
        "internalType": "address[]",
        "name": "nfpms",
        "type": "address[]"
      },
      {
        "indexed": false,
        "internalType": "bool",
        "name": "isWhitelisted",
        "type": "bool"
      }
    ],
    "name": "WhitelistNfpmsUpdated",
    "type": "event"
  },
  {
    "anonymous": false,
    "inputs": [
      {
        "indexed": false,
        "internalType": "address[]",
        "name": "swapRouters",
        "type": "address[]"
      },
      {
        "indexed": false,
        "internalType": "bool",
        "name": "isWhitelisted",
        "type": "bool"
      }
    ],
    "name": "WhitelistSwapRoutersUpdated",
    "type": "event"
  },
  {
    "anonymous": false,
    "inputs": [
      {
        "indexed": false,
        "internalType": "address[]",
        "name": "targets",
        "type": "address[]"
      },
      {
        "indexed": false,
        "internalType": "bool",
        "name": "isWhitelisted",
        "type": "bool"
      }
    ],
    "name": "WhitelistTargetsUpdated",
    "type": "event"
  },
  {
    "inputs": [],
    "name": "feeRecipient",
    "outputs": [
      {
        "internalType": "address",
        "name": "",
        "type": "address"
      }
    ],
    "stateMutability": "view",
    "type": "function"
  },
  {
    "inputs": [
      {
        "internalType": "address",
        "name": "_owner",
        "type": "address"
      },
      {
        "internalType": "address[]",
        "name": "_whitelistTargets",
        "type": "address[]"
      },
      {
        "internalType": "address[]",
        "name": "_whitelistCallers",
        "type": "address[]"
      },
      {
        "internalType": "address",
        "name": "_feeRecipient",
        "type": "address"
      },
      {
        "internalType": "uint16",
        "name": "_platformFeeBasisPoint",
        "type": "uint16"
      },
      {
        "internalType": "address[]",
        "name": "_whitelistNfpms",
        "type": "address[]"
      },
      {
        "internalType": "address[]",
        "name": "_whitelistSwapRouters",
        "type": "address[]"
      }
    ],
    "name": "initialize",
    "outputs": [],
    "stateMutability": "nonpayable",
    "type": "function"
  },
  {
    "inputs": [],
    "name": "isVaultPaused",
    "outputs": [
      {
        "internalType": "bool",
        "name": "",
        "type": "bool"
      }
    ],
    "stateMutability": "view",
    "type": "function"
  },
  {
    "inputs": [
      {
        "internalType": "address",
        "name": "caller",
        "type": "address"
      }
    ],
    "name": "isWhitelistedCaller",
    "outputs": [
      {
        "internalType": "bool",
        "name": "",
        "type": "bool"
      }
    ],
    "stateMutability": "view",
    "type": "function"
  },
  {
    "inputs": [
      {
        "internalType": "address",
        "name": "nfpm",
        "type": "address"
      }
    ],
    "name": "isWhitelistedNfpm",
    "outputs": [
      {
        "internalType": "bool",
        "name": "",
        "type": "bool"
      }
    ],
    "stateMutability": "view",
    "type": "function"
  },
  {
    "inputs": [
      {
        "internalType": "address",
        "name": "swapRouter",
        "type": "address"
      }
    ],
    "name": "isWhitelistedSwapRouter",
    "outputs": [
      {
        "internalType": "bool",
        "name": "",
        "type": "bool"
      }
    ],
    "stateMutability": "view",
    "type": "function"
  },
  {
    "inputs": [
      {
        "internalType": "address",
        "name": "target",
        "type": "address"
      }
    ],
    "name": "isWhitelistedTarget",
    "outputs": [
      {
        "internalType": "bool",
        "name": "",
        "type": "bool"
      }
    ],
    "stateMutability": "view",
    "type": "function"
  },
  {
    "inputs": [],
    "name": "maxPositions",
    "outputs": [
      {
        "internalType": "uint16",
        "name": "",
        "type": "uint16"
      }
    ],
    "stateMutability": "view",
    "type": "function"
  },
  {
    "inputs": [],
    "name": "minTokenPrecision",
    "outputs": [
      {
        "internalType": "uint8",
        "name": "",
        "type": "uint8"
      }
    ],
    "stateMutability": "view",
    "type": "function"
  },
  {
    "inputs": [],
    "name": "owner",
    "outputs": [
      {
        "internalType": "address",
        "name": "",
        "type": "address"
      }
    ],
    "stateMutability": "view",
    "type": "function"
  },
  {
    "inputs": [],
    "name": "platformFeeBasisPoint",
    "outputs": [
      {
        "internalType": "uint16",
        "name": "",
        "type": "uint16"
      }
    ],
    "stateMutability": "view",
    "type": "function"
  },
  {
    "inputs": [],
    "name": "renounceOwnership",
    "outputs": [],
    "stateMutability": "nonpayable",
    "type": "function"
  },
  {
    "inputs": [
      {
        "internalType": "address",
        "name": "newFeeRecipient",
        "type": "address"
      }
    ],
    "name": "setFeeRecipient",
    "outputs": [],
    "stateMutability": "nonpayable",
    "type": "function"
  },
  {
    "inputs": [
      {
        "internalType": "uint16",
        "name": "_maxPositions",
        "type": "uint16"
      }
    ],
    "name": "setMaxPositions",
    "outputs": [],
    "stateMutability": "nonpayable",
    "type": "function"
  },
  {
    "inputs": [
      {
        "internalType": "uint8",
        "name": "precision",
        "type": "uint8"
      }
    ],
    "name": "setMinTokenPrecision",
    "outputs": [],
    "stateMutability": "nonpayable",
    "type": "function"
  },
  {
    "inputs": [
      {
        "internalType": "uint16",
        "name": "basisPoints",
        "type": "uint16"
      }
    ],
    "name": "setPlatformFeeBasisPoint",
    "outputs": [],
    "stateMutability": "nonpayable",
    "type": "function"
  },
  {
    "inputs": [
      {
        "internalType": "bool",
        "name": "_isVaultPaused",
        "type": "bool"
      }
    ],
    "name": "setVaultPaused",
    "outputs": [],
    "stateMutability": "nonpayable",
    "type": "function"
  },
  {
    "inputs": [
      {
        "internalType": "address[]",
        "name": "callers",
        "type": "address[]"
      },
      {
        "internalType": "bool",
        "name": "_isWhitelisted",
        "type": "bool"
      }
    ],
    "name": "setWhitelistCallers",
    "outputs": [],
    "stateMutability": "nonpayable",
    "type": "function"
  },
  {
    "inputs": [
      {
        "internalType": "address[]",
        "name": "nfpms",
        "type": "address[]"
      },
      {
        "internalType": "bool",
        "name": "_isWhitelisted",
        "type": "bool"
      }
    ],
    "name": "setWhitelistNfpms",
    "outputs": [],
    "stateMutability": "nonpayable",
    "type": "function"
  },
  {
    "inputs": [
      {
        "internalType": "address[]",
        "name": "swapRouters",
        "type": "address[]"
      },
      {
        "internalType": "bool",
        "name": "_isWhitelisted",
        "type": "bool"
      }
    ],
    "name": "setWhitelistSwapRouters",
    "outputs": [],
    "stateMutability": "nonpayable",
    "type": "function"
  },
  {
    "inputs": [
      {
        "internalType": "address[]",
        "name": "targets",
        "type": "address[]"
      },
      {
        "internalType": "bool",
        "name": "_isWhitelisted",
        "type": "bool"
      }
    ],
    "name": "setWhitelistTargets",
    "outputs": [],
    "stateMutability": "nonpayable",
    "type": "function"
  },
  {
    "inputs": [
      {
        "internalType": "address",
        "name": "newOwner",
        "type": "address"
      }
    ],
    "name": "transferOwnership",
    "outputs": [],
    "stateMutability": "nonpayable",
    "type": "function"
  },
  {
    "inputs": [
      {
        "internalType": "address",
        "name": "",
        "type": "address"
      }
    ],
    "name": "whitelistedCallers",
    "outputs": [
      {
        "internalType": "bool",
        "name": "",
        "type": "bool"
      }
    ],
    "stateMutability": "view",
    "type": "function"
  },
  {
    "inputs": [
      {
        "internalType": "address",
        "name": "",
        "type": "address"
      }
    ],
    "name": "whitelistedNfpms",
    "outputs": [
      {
        "internalType": "bool",
        "name": "",
        "type": "bool"
      }
    ],
    "stateMutability": "view",
    "type": "function"
  },
  {
    "inputs": [
      {
        "internalType": "address",
        "name": "",
        "type": "address"
      }
    ],
    "name": "whitelistedSwapRouters",
    "outputs": [
      {
        "internalType": "bool",
        "name": "",
        "type": "bool"
      }
    ],
    "stateMutability": "view",
    "type": "function"
  },
  {
    "inputs": [
      {
        "internalType": "address",
        "name": "",
        "type": "address"
      }
    ],
    "name": "whitelistedTargets",
    "outputs": [
      {
        "internalType": "bool",
        "name": "",
        "type": "bool"
      }
    ],
    "stateMutability": "view",
    "type": "function"
  }
]
